basicnanoclient/__init__.py
basicnanoclient/rpc.py
basicnanoclient/utils.py
basicnanoclient/wallet.py
basicnanoclient-0.5.0.dist-info/LICENSE
basicnanoclient-0.5.0.dist-info/METADATA
basicnanoclient-0.5.0.dist-info/WHEEL
basicnanoclient-0.5.0.dist-info/top_level.txt
basicnanoclient-0.5.0.dist-info/RECORD
