Metadata-Version: 2.1
Name: basicnanoclient
Version: 0.5.0
Summary: Nano RPC python client
Home-page: https://github.com/nanoswap/basicnanoclient
Author: Nathaniel Schultz
Author-email: Nathaniel Schultz <nate@nanoswap.finance>
License: This is free and unencumbered software released into the public domain.
Project-URL: Bug Tracker, https://github.com/nanoswap/basicnanoclient/issues
Classifier: Programming Language :: Python :: 3
Classifier: License :: OSI Approved :: The Unlicense (Unlicense)
Requires-Python: >=3.11
License-File: LICENSE
Requires-Dist: requests
Requires-Dist: pynacl
Requires-Dist: ed25519-blake2b
Requires-Dist: ed25519
Requires-Dist: bitstring
Requires-Dist: setuptools
Requires-Dist: mkdocs
Requires-Dist: mkdocstrings
Requires-Dist: mkdocstrings-python
